harlequin_adbc/__init__.py
harlequin_adbc/adapter.py
harlequin_adbc/cli_options.py
harlequin_adbc/py.typed
harlequin_adbc-0.1.2.dist-info/LICENSE
harlequin_adbc-0.1.2.dist-info/METADATA
harlequin_adbc-0.1.2.dist-info/WHEEL
harlequin_adbc-0.1.2.dist-info/entry_points.txt
harlequin_adbc-0.1.2.dist-info/RECORD
