Metadata-Version: 2.1
Name: harlequin-adbc
Version: 0.1.2
Summary: A Harlequin adapter for ADBC drivers.
Home-page: https://harlequin.sh
License: MIT
Author: Tyler Hillery
Author-email: tylerhillery@users.noreply.github.com
Requires-Python: >=3.9,<4.0
Classifier: License :: OSI Approved :: MIT License
Classifier: Programming Language :: Python :: 3
Classifier: Programming Language :: Python :: 3.9
Classifier: Programming Language :: Python :: 3.10
Classifier: Programming Language :: Python :: 3.11
Provides-Extra: flightsql
Provides-Extra: postgresql
Provides-Extra: snowflake
Provides-Extra: sqlite
Requires-Dist: adbc-driver-flightsql (>=0.9) ; extra == "flightsql"
Requires-Dist: adbc-driver-manager (>=0.9.0)
Requires-Dist: adbc-driver-postgresql (>=0.9) ; extra == "postgresql"
Requires-Dist: adbc-driver-snowflake (>=0.9) ; extra == "snowflake"
Requires-Dist: adbc-driver-sqlite (>=0.9) ; extra == "sqlite"
Requires-Dist: harlequin (>=1.7,<3)
Requires-Dist: pyarrow (>=14.0.0)
Project-URL: Repository, https://github.com/TylerHillery/harlequin-adbc
